{
  "adminController": {
    "acl": {
      "all": [
        "index",
        "login",
        "settings",
        "logout"
      ],
      "authorize": [],
      "guest": [],
      "admin": []
    },
    "description": "asdasdasd"
  },
  "accountController": {
    "acl": {
      "all": [],
      "authorize": [
        "index",
        "logout",
        "confirm"
      ],
      "guest": [
        "login",
        "registration"
      ],
      "admin": []
    },
    "description": "asdasdasd"
  },
  "mainController": {
    "acl": {
      "all": [
        "privacy",
        "rules",
        "index"
      ],
      "authorize": [],
      "guest": [],
      "admin": []
    },
    "description": "asdasdasd"
  },
  "apiController": {
    "acl": {
      "all": [
        "index",
        "email",
        "settings",
        "acl"
      ],
      "authorize": [],
      "guest": [],
      "admin": []
    },
    "description": "asdasdasd"
  }
}